pytonik_time_ago/__init__.py
pytonik_time_ago/timeago.py
pytonik_time_ago-0.2.0.dist-info/LICENSE.txt
pytonik_time_ago-0.2.0.dist-info/METADATA
pytonik_time_ago-0.2.0.dist-info/WHEEL
pytonik_time_ago-0.2.0.dist-info/top_level.txt
pytonik_time_ago-0.2.0.dist-info/RECORD
