Metadata-Version: 2.1
Name: pytonik-time-ago
Version: 0.2.0
Summary: pytonik date and time ago readable format
Home-page: https://github.com/pytonik/pytonik_time_ago
Author: pytonik
Author-email: info@pytonik.com
Maintainer: Emmanuel Essien
Maintainer-email: emmamartinscm@gmail.com
License: Apache 2.0
Keywords: mvc,oop,module,framework,pytonik,time,date,timeago,readable time
Platform: UNKNOWN
Classifier: Environment :: Console
Classifier: License :: OSI Approved :: MIT License
Classifier: Environment :: Web Environment
Classifier: Intended Audience :: End Users/Desktop
Classifier: Intended Audience :: Developers
Classifier: Intended Audience :: System Administrators
Classifier: License :: OSI Approved :: Python Software Foundation License
Classifier: Programming Language :: Python
Classifier: Topic :: Office/Business
Classifier: Intended Audience :: Developers
Classifier: License :: OSI Approved :: MIT License
Classifier: Operating System :: OS Independent
Classifier: Programming Language :: Python :: 2.7
Classifier: Programming Language :: Python :: 3
Classifier: Programming Language :: Python :: 3.4
Classifier: Programming Language :: Python :: 3.5
Classifier: Programming Language :: Python :: 3.6
Classifier: Programming Language :: Python :: 3.7
Classifier: Programming Language :: Python :: 3.8
Classifier: Programming Language :: Python
Requires-Python: >=2.7, >=3
